[
  {
    "title": "EM1 - Galvanometer",
    "image": "images/em1galvano.jpg",
    "description": "detects or measures small currents and voltages by using a moving coil.",
    "link": "subpages/em1.html",
    "infotext": "Attachments are available to change the sensitivity of the galvanometer. The box containing the attachments lies next to it on the shelf."  
},
  {
    "title": "EM2 - Audio Oscillator",
    "image": "images/em2audioosc.jpg",
    "description": "Different circuits and components are used to create different waveform shapes (sine, square, triangle, etc.).  ",
    "link": "subpages/em2.html"
  },
  {
    "title": "EM3 - Variac",
    "image": "images/em3variac.jpg",
    "description": "Power supply used to provide a variable AC voltage output, allowing for precise adjustments of voltage levels in various applications.",
    "link": "subpages/em3.html"
  },
   {
    "title": "EM21 - Charging by Induction",
    
    "description": "Shows charging by induction.",
    "link": "subpages/em21.html"
  },

  {
    "title": "EM22 - Faraday's Ice Pail",
    "description": "Shows distribution of charge.",
    "image": "images/em22faradice.jpg",
    "link": "subpages/em22.html"
  },
  {
    "title": "EM23 - Charge On Concentric Shells",
    "image": "images/em23cshellcharge.jpg",
    "description": "Shows the distribution of charge on concentric shells.",
    "link": "subpages/em23.html"
  },
  {
    "title": "EM24 - Center of Gravity",
    "image": "images/em24irregshapecharge.jpg",
    "description": "Shows the distribution of charge on irregularly shaped objects..",
    "link": "subpages/em24.html"
  },
  {
    "title": "EM25 - Charging By Induction",
    "image": "images/em25chbyinduc.jpg",
    "description": "Shows charging by induction.",
    "link": "subpages/em25.html"
  },
  {
    "title": "EM26 - Van de Graaf Generators",
    "image": "images/em26vdgraaf.jpg",
    "description": "Generates static electricity.",
    "link": "subpages/em26.html"
  },  
  {
    "title": "EM27 - Box Of Electrostatic Demos",
    "image": "images/em27electrostat.jpg",
    "description": "Demonstrates concepts in electrostatics.",
    "link": "subpages/em27.html"
  },  
  {
    "title": "EM28 - Capacitance",
    "image": "images/em28cap.jpg",
    "description": "Demonstrates the concept of capacitance.",
    "link": "subpages/em28.html"
  },  
  {
    "title": "EM29 -Capacitor With Dielectric",
    "image": "images/em29capwithdi.jpg",
    "description": "Shows the effect of a dielectric on capacitance.",
    "link": "subpages/em29.html"
  },
  {
    "title": "EM30 - Capacitor With Ball",
    "image": "images/em30capwithball.jpg",
    "description": "Simple electrostatics demonstration.",
    "link": "subpages/em30.html"
  },
  {
    "title": "EM31 - Spark Gaps",
    "image": "images/em31sparkgaps.jpg",
    "description": "Amusing electrostatics demonstration.",
    "link": "subpages/em31.html"
  },
  {
    "title": "EM32 - Variable Capacitors",
    "image": "images/em32varcap.jpg",
    "description": "Shows the effect of plate distance on capacitance.",
    "link": "subpages/em32.html"
  },
  {
    "title": "EM33 - Kelvin Current Balance",
    "image": "images/em33kelcurbal.jpg",
    "description": "a device, also known as an ampere balance or current balance, used to precisely measure electric current",
    "link": "subpages/em33.html"
  },
  {
    "title": "EM34- The Electrostatic Field",
    "image": "images/em34esfield.jpg",
    "description": "Shows the direction of the electrostatic field.",
    "link": "subpages/em34.html"
  },  
  {
    "title": "EM35 - The Electrophorous",
    "image": "images/em35electropho.jpg",
    "description": "Illustrates the basic principle of many electrostatic machines.",
    "link": "subpages/em35.html"
  },
  {
    "title": "M44 - Tangential motion",
    "image": "images/m44tangent.jpg",
    "description": "Demonstrates Newton's First Law.",
    "link": "subpages/m44.html"
  },  
  {
    "title": "EM36 - Triboelectricity",
    "image": "images/em36triboelec.jpg",
    "description": "Basic experiments on electrification by contact and friction.",
    "link": "subpages/em36.html"
  },    
   {
    "title": "EM37 - Swinging Pith Ball",
    "image": "images/em37swingpithball.jpg",
    "description": "Simple electrostatics demonstration.",
    "link": "subpages/em37.html"
  },
  {
    "title": "EM38 - Proof Planes",
    "image": "images/em38proofplane.jpg",
    "description": "Used for transferring charge.",
    "link": "subpages/em38.html"
  },
    {
    "title": "EM39 - Gold Leaf Electroscopes",
    "image": "images/em39electroscope.jpg",
    "description": "Used to measure potential difference.",
    "link": "subpages/em39.html"
  },
  {
    "title": "EM40 - Whimshurst Machines",
    "image": "images/em40whimhurst.jpg",
    "description": "Used to generate static electricity.",
    "link": "subpages/em40.html"
  },
  {
    "title": "EM51 - Resistance",
    "image": "images/em51resistance.jpg",
    "description": "Shows the difference between resistance in series and resistance in parallel.",
    "link": "subpages/em51.html"
  },
  {
    "title": "EM55 - Back EMF Of Motor",
    "image": "images/em55backemf.jpg",
    "description": "Demonstrates back EMF.",
    "link": "subpages/em55.html"
  },
  {
    "title": "EM57 - Time-Dependent Currents",
    "image": "images/em57tdcurrents.jpg",
    "description": "Shows that a capacitor “passes” alternating current but not direct current.",
    "link": "subpages/em57.html"
  },
{
    "title": "EM60 - Time Constant",
    "image": "images/em60tconst.jpg",
    "description": "Demonstrates the time constant of a capacitor.",
    "link": "subpages/em60.html"
  },
{
    "title": "EM61 - Variable Capacitor",
    "image": "images/em61varcap.jpg",
    "description": "Enables varying capacitance for demonstrations.",
    "link": "subpages/em61.html"
  },
{
    "title": "M68 - Equal Masses on Double Pulley",
    "image": "images/m68doublepulley.jpg",
    "description": "Illustrates Newton's 1st law in a less intuitive setup.",
    "link": "subpages/m68.html"
  },
{
    "title": "M69 - Adjustable Pulley",
    "image": "images/m69adjustpulley.jpg",
    "description": "A pulley with adjustable height.",
    "link": "subpages/m69.html"
  },
{
    "title": "M80 - Trolleys",
    "image": "images/m80trolleys.jpg",
    "description": "Demonstrates elastic collisions.",
    "link": "subpages/m80.html"
  },
{
    "title": "M81 - Newton's Cradle",
    "image": "images/m81newtoncradle.jpg",
    "description": "Demonstrates the conservation of momentum and kinetic energy in elastic collisions.",
    "link": "subpages/m81.html"
  },
{
    "title": "M82 - Mini Newton's Cradle",
    "image": "images/m82minicradle.jpg",
    "description": "Demonstrates the conservation of momentum and kinetic energy in elastic collisions.",
    "link": "subpages/m82.html"
  },
{
    "title": "M83 - Balls on Rails",
    "image": "images/m83ballsonrails.jpg",
    "description": "Demonstrates the conservation of momentum and kinetic energy in elastic collisions.",
    "link": "subpages/m83.html"
  },
{
    "title": "M84 - Inelastic collisions",
    "image": "images/m84inelastic.jpg",
    "description": "Demonstrates how momentum and kinetic energy are not conserved in inelastic collisions.",
    "link": "subpages/m84.html"
  },
  {
    "title": "M85 - conservation of Momentum",
    "image": "images/m85consmom.jpg",
    "description": "Demonstrates conservation of momentum.",
    "link": "subpages/m85.html"
  },                         
 {
    "title": "M86 - Elastic & Inelastic collisions",
    "image": "images/m86inelastic.jpg",
    "description": "Demonstrates the difference between elastic and inelastic collisions.",
    "link": "subpages/m86.html"
  },                         
 {
    "title": "M87 - Superballs",
    "image": "images/m87superballs.jpg",
    "description": "To show objects with high coefficients of restitution.",
    "link": "subpages/m87.html"
  },                         
 {
    "title": "M88- Conservation of Momentum",
    "image": "images/m88momcons.jpg",
    "description": "Demonstrates conservaton of momentum with a less intuitive setup.",
    "link": "subpages/m88.html"
  },
  {
    "title": "M89- Air Track",
    "image": "images/m89airtrack.jpg",
    "description": "Demonstrates elastic collisions.",
    "link": "subpages/m89.html"
  },                          
 {
    "title": "M90 - Rocket and Block",
    "image": "images/m90rocketblock.jpg",
    "description": "Demonstrates transfer of energy in elastic and inelastic collisions.",
    "link": "subpages/m90.html"
  },                         
 {
    "title": "M91 - Air Table",
    "image": "images/m91airtable.jpg",
    "description": "Demonstrates elastic collisions.",
    "link": "subpages/m91.html"
  },                         
 {
    "title": "M92 - Water Rocket",
    "image": "images/m92waterrocket.jpg",
    "description": "Demonstrates how conservation of momentum is behind the working of rockets.",
    "link": "subpages/m92.html"
  },                         
 {
    "title": "M93 - Balls on Tracks",
    "image": "images/m93ballsontracks.jpg",
    "description": "An interesting and somewhat counter-intuitive experiment.",
    "link": "subpages/m93.html"
  },                         
 {
    "title": "M100 - Attwood's Machine",
    "image": "images/m100attwoods.jpg",
    "description": "An interesting rotational device to demonstrate the principles of motion with constant acceleration.",
    "link": "subpages/m100.html"
  },                         
 {
    "title": "M101 - Crowbar",
    "image": "images/m101crowbar.jpg",
    "description": "Illustrates the idea of moments.",
    "link": "subpages/m101.html"
  },                         
 {
    "title": "M102 - Rotational Motion",
    "image": "images/m102rotation.jpg",
    "description": "Demonstrates various principles of rotational motion.",
    "link": "subpages/m102.html"
  },                         
 {
    "title": "M103 - conservation of Momentum: Jet Propulsion",
    "image": "images/m103jetprop.jpg",
    "description": "Demonstrates conservation of momentum.",
    "link": "subpages/m103.html"
  },                         
 {
    "title": "M104 - Centrifugal Force",
    "image": "images/m104centrifug.jpg",
    "description": "Demonstrates the centripetal force on and centrifugal reaction by a constrained rotated object.",
    "link": "subpages/m104.html"
  },                         
 {
    "title": "M105 - Rotating Candles",
    "image": "images/m105rotcandles.jpg",
    "description": "Demonstrates the interplay between buoyancy, centripetal force, and the properties of a flame.",
    "link": "subpages/m105.html"
  },                         
 {
    "title": "M106 - Large Gyroscope",
    "image": "images/m106gyrolarge.jpg",
    "description": "Demonstrates various rotational principles.",
    "link": "subpages/m106.html"
  },                         
 {
    "title": "M108 - Angular Momentum",
    "image": "images/m108angmom.jpg",
    "description": "Demonstrates various rotational principles.",
    "link": "subpages/m108.html"
  },                         
 {
    "title": "M109 - Small Gyroscopes",
    "image": "images/m109gyrosmall.jpg",
    "description": "Shows the working of gyroscopes.",
    "link": "subpages/m109.html"
  },                         
 {
    "title": "M110 - Rotational Motion",
    "image": "images/m110rotmot.jpg",
    "description": "Demonstrates the forces resulting from rotational motion.",
    "link": "subpages/m110.html"
  },                         
 {
    "title": "M114 - Celts",
    "image": "images/m114celts.jpg",
    "description": "Demonstrates a unique spin reversal behavior.",
    "link": "subpages/m114.html"
  },                         
 {
    "title": "M120 - Hooke's Law",
    "image": "images/m120hooks.jpg",
    "description": "Demonstrates Hooke's Law.",
    "link": "subpages/m120.html"
  },                         
 {
    "title": "M121 - Elastic Limit",
    "image": "images/m121elimit.jpg",
    "description": "Demonstrates Hooke's Law and the elastic limit of a material.",
    "link": "subpages/m121.html"
  },                         
 {
    "title": "M122 - Modulus of Rigidity",
    "image": "images/m122rigidity.jpg",
    "description": "Demonstrates the concepts of torsion and the modulus of rigidity.",
    "link": "subpages/m122.html"
  },                         
 {
    "title": "M130 - Harmonic motion",
    "image": "images/m130harmonic.jpg",
    "description": "Shows the equivalence of two types of simple harmonic motion.",
    "link": "subpages/m130.html"
  },                         
 {
    "title": "M131 - Cantilever Oscillations",
    "image": "images/m131cantilever.jpg",
    "description": "Demonstrates free-end oscillations.",
    "link": "subpages/m131.html"
  },                         
 {
    "title": "M132 - Ball on a spring (SHM)",
    "image": "images/m132ballonspring.jpg",
    "description": "Demonstrates Simple Harmonic Motion with a ball on a spring.",
    "link": "subpages/m132.html"
  },                         
 {
    "title": "M133 - Oscillating ball on slope (SHM)",
    "image": "images/m133oscball.jpg",
    "description": "Demonstrates Harmonic Motion.",
    "link": "subpages/m133.html"
  },                         
 {
    "title": "M140 - Simple Pendulums",
    "image": "images/m140simpend.jpg",
    "description": "Demonstrates Oscillations using a Simple Pendulum.",
    "link": "subpages/m140.html"
  },                         
 {
    "title": "M141 - Period of Oscillation",
    "image": "images/m141period.jpg",
    "description": "Shows that the period of oscillation is independent of mass but proportional to the length of string.",
    "link": "subpages/m141.html"
  },                         
 {
    "title": "M142 - Whirligig Pendulum",
    "image": "images/m142whirligig.jpg",
    "description": "Mostly Entertaining.  Shows the conversion energy (like wind or elastic energy in a string) into rotational motion.",
    "link": "subpages/m142.html"
  },                         
 {
    "title": "M143 - Galilieo's Pendulum",
    "image": "images/m143galpend.jpg",
    "description": "Shows the transformation from potential energy to kinetic energy and back again.",
    "link": "subpages/m143.html"
  },
  {
    "title": "M144 - Ballistic Pendulum",
    "image": "images/m144balpend.jpg",
    "description": "Demonstrates conservation of energy.",
    "link": "subpages/m144.html"
  },
  {
    "title": "M145 - Probabalistic Pendulum",
    "image": "images/m145probapend.jpg",
    "description": "Demonstrates conservation of energy.",
    "link": "subpages/m145.html"
  },
  {
    "title": "M146 - Ring Pendulum",
    "image": "images/m146ringpend.jpg",
    "description": "Shows that a ring and a straight pendulum have the same period if the length of the pendulum is equal to the diameter of the ring.",
    "link": "subpages/m146.html"
  },
  {
    "title": "M147 - Different Lengths Pendulum",
    "image": "images/m147difflenthpend.jpg",
    "description": "Demonstrates how the period of a pendulum depends on its length.",
    "link": "subpages/m147.html"
  },
  {
    "title": "M148 - Oscillating Lamina",
    "image": "images/m148osclam.jpg",
    "description": "Demonstrates how changing the moment of inertia affects the frequency of oscillation.",
    "link": "subpages/m148.html"
  },
  {
    "title": "M149 - Double Pendulum",
    "image": "images/m149doubpend.jpg",
    "description": "This is an example of a chaotic system that is highly sensitive to initial conditions.",
    "link": "subpages/m149.html"
  },
  {
    "title": "M150 - Two Rod Pendulums",
    "image": "images/m150tworodpend.jpg",
    "description": "A comparison of the acclerations of pendulums with and without masses attached to their lower ends.",
    "link": "subpages/m150.html"
  },
  {
    "title": "M151 - Giant Pendulum",
    "image": "images/m151giantpend.jpg",
    "description": "This demonstrates conservation of energy in a dramatic way.",
    "link": "subpages/m151.html"
  },
  {
    "title": "M160 - Wilberforce Pendulum",
    "image": "images/m160wilberpend.jpg",
    "description": "Shows the normal modes of a Wilberforce pendulum.",
    "link": "subpages/m160.html"
  },
  {
    "title": "M161 - Adjustable Wilberforce Pendulum",
    "image": "images/m161adjwilberpend.jpg",
    "description": "This demonstrates the effect of changing the moment of inertia on the beat frequency of a Wilberforce pendulum.",
    "link": "subpages/m161.html"
  },
  {
    "title": "M162 - Simple Coupled Oscillator",
    "image": "images/m162couposc.jpg",
    "description": "Demonstration of a coupled oscillator.",
    "link": "subpages/m162.html"
  },
  {
    "title": "M163 - Oscillator Coupled by Mass",
    "image": "images/m163masscouposc.jpg",
    "description": "Demonstration of coupled oscillators.",
    "link": "subpages/m163.html"
  },
  {
    "title": "M164 - Oscillator Coupled by Rod",
    "image": "images/m164rodcouposc.jpg",
    "description": "Demonstration of coupled oscillators.",
    "link": "subpages/m164.html"
  },
  {
    "title": "M165 - Oscillator Coupled by Bar",
    "image": "images/m165barcouposc.jpg",
    "description": "Demonstration of coupled oscillators.",
    "link": "subpages/m165.html"
  },
  {
    "title": "M166 - Pair of Wilberforce Pendulums",
    "image": "images/m166wilberpair.jpg",
    "description": "Demonstration of coupled oscillators.",
    "link": "subpages/m166.html"
  },
  {
    "title": "M170 - Resonance",
    "image": "images/m170resonance.jpg",
    "description": "Demonstration resonance.",
    "link": "subpages/m170.html"
  },
  {
    "title": "M171 - Resonance Oscillations",
    "image": "images/m171resonance.jpg",
    "description": "Demonstration resonance.",
    "link": "subpages/m171.html"
  },
  {
    "title": "M172 - Driven Oscillations",
    "image": "images/m172drivenpendulum.jpg",
    "description": "Demonstration resonance.",
    "link": "subpages/m172.html"
  },
  {
    "title": "M180 - Chemical balance",
    "image": "images/m180chembalance.jpg",
    "description": "Used to illustrate the sensitivity and stability of a chemical balance.",
    "link": "subpages/m180.html"
  },
  {
    "title": "M181 - Large Vernier Callipers",
    "image": "images/m181Largevernier.jpg",
    "description": "Large model of Vernier calipers.",
    "link": "subpages/m181.html"
  },
  {
    "title": "M182 - Large Slide Rule",
    "image": "images/m182sliderule.jpg",
    "description": "A large slide rule.",
    "link": "subpages/m182.html"
  },
  {
    "title": "M183 - Model of a Vernier Scale",
    "image": "images/m183vernierscale.jpg",
    "description": "For teaching measurement and how to read a vernier scale.",
    "link": "subpages/m183.html"
  },
  {
    "title": "M184 - Model Micrometer Screwgauge",
    "image": "images/m184micrometer.jpg",
    "description": "Large model of a Micrometer Screwguage.",
    "link": "subpages/m184.html"
  },
  {
    "title": "M185 - Spherometer",
    "image": "images/m185spherometer.jpg",
    "description": "Large model of a spherometer.",
    "link": "subpages/m185.html"
  },
  {
    "title": "M186 - Vector Arrows",
    "image": "images/m186vectors.jpg",
    "description": "Use them to demonstrate vectors in three dimensions.",
    "link": "subpages/m186.html"
  }
  
  
  
  
  
]
